web1/__init__.py
web1/asp_state.py
web1/asp_validators.py
web1/csharp.py
web1/php_basics.py
web1/php_db.py
web1/php_form.py
webb1-0.3.6.dist-info/METADATA
webb1-0.3.6.dist-info/WHEEL
webb1-0.3.6.dist-info/top_level.txt
webb1-0.3.6.dist-info/RECORD
