Metadata-Version: 2.4
Name: webb1
Version: 0.3.6
Summary: Web Development Practical Notes: PHP, C#, ASP.NET
Author: Unknown
Requires-Python: >=3.7
Dynamic: author
Dynamic: description
Dynamic: description-content-type
Dynamic: requires-python
Dynamic: summary
